KafkaLibrary/Consumer.py
KafkaLibrary/Producer.py
KafkaLibrary/__init__.py
KafkaLibrary/version.py
robotframework_kafkalibrary-0.0.3.dist-info/LICENSE
robotframework_kafkalibrary-0.0.3.dist-info/METADATA
robotframework_kafkalibrary-0.0.3.dist-info/WHEEL
robotframework_kafkalibrary-0.0.3.dist-info/top_level.txt
robotframework_kafkalibrary-0.0.3.dist-info/RECORD
