Metadata-Version: 2.1
Name: robotframework-kafkalibrary
Version: 0.0.3
Summary: Kafka library for Robot Framework
Home-page: https://github.com/s4int/robotframework-KafkaLibrary
Author: Marcin Mierzejewski
Author-email: <mmierz@gmail.com>
License: Apache License 2.0
Keywords: robotframework testing kafka
Platform: any
Classifier: Development Status :: 4 - Beta
Classifier: License :: OSI Approved :: Apache Software License
Classifier: Operating System :: OS Independent
Classifier: Programming Language :: Python
Classifier: Topic :: Software Development :: Testing
Requires-Dist: robotframework (>=2.6.0)
Requires-Dist: kafka-python
